tg_bot_discussion/__init__.py
tg_bot_discussion/main.py
tg_bot_discussion-0.1.1.dist-info/licenses/LICENSE
tg_bot_discussion-0.1.1.dist-info/METADATA
tg_bot_discussion-0.1.1.dist-info/WHEEL
tg_bot_discussion-0.1.1.dist-info/top_level.txt
tg_bot_discussion-0.1.1.dist-info/RECORD
