Metadata-Version: 2.4
Name: tg-bot-discussion
Version: 0.1.1
Summary: Telegram Bot framework based on native Python-library for the Telegram Bot API.
Author: BorisPlus
Keywords: python Telegram-bot framework
Classifier: Programming Language :: Python :: 3.11
Classifier: License :: OSI Approved :: MIT License
Classifier: Operating System :: OS Independent
Requires-Python: >=3.9
License-File: LICENSE
Dynamic: author
Dynamic: classifier
Dynamic: description
Dynamic: description-content-type
Dynamic: keywords
Dynamic: license-file
Dynamic: requires-python
Dynamic: summary
